Metadata-Version: 2.1
Name: AminoLab
Version: 2.5
Summary: A library for aminoapps.com to create Amino bots.
Home-page: https://github.com/LilZevi/AminoLab
Author: LilZevi
Author-email: elegantlyakaintelligent@gmail.com
License: MIT
Download-URL: https://github.com/LilZevi/AminoLab/archive/refs/heads/main.zip
Keywords: aminoapps,amino-py,amino,amino-bot,narvii,api,python,python3,python3.x,lilzevi,botamino,aminoapp
Platform: UNKNOWN
